yawast/__init__.py
yawast/__main__.py
yawast/_static_version.py
yawast/_version.py
yawast/command_line.py
yawast/main.py
yawast/commands/__init__.py
yawast/commands/dns.py
yawast/commands/scan.py
yawast/commands/ssl.py
yawast/commands/utils.py
yawast/external/__init__.py
yawast/external/get_char.py
yawast/external/memory_size.py
yawast/external/retirejs.py
yawast/external/spinner.py
yawast/external/total_size.py
yawast/reporting/__init__.py
yawast/reporting/enums.py
yawast/reporting/issue.py
yawast/reporting/reporter.py
yawast/resources/common_dir.txt
yawast/resources/common_file.txt
yawast/resources/common_ports.json
yawast/resources/http-protocol-methods.txt
yawast/resources/srv.txt
yawast/resources/subdomains.txt
yawast/scanner/__init__.py
yawast/scanner/session.py
yawast/scanner/cli/__init__.py
yawast/scanner/cli/dns.py
yawast/scanner/cli/http.py
yawast/scanner/cli/network.py
yawast/scanner/cli/ssl_internal.py
yawast/scanner/cli/ssl_labs.py
yawast/scanner/cli/ssl_sweet32.py
yawast/scanner/plugins/__init__.py
yawast/scanner/plugins/evidence.py
yawast/scanner/plugins/result.py
yawast/scanner/plugins/dns/__init__.py
yawast/scanner/plugins/dns/basic.py
yawast/scanner/plugins/dns/caa.py
yawast/scanner/plugins/dns/dnssec.py
yawast/scanner/plugins/dns/network_info.py
yawast/scanner/plugins/dns/srv.py
yawast/scanner/plugins/dns/subdomains.py
yawast/scanner/plugins/http/__init__.py
yawast/scanner/plugins/http/error_checker.py
yawast/scanner/plugins/http/file_search.py
yawast/scanner/plugins/http/http_basic.py
yawast/scanner/plugins/http/response_scanner.py
yawast/scanner/plugins/http/retirejs.py
yawast/scanner/plugins/http/special_files.py
yawast/scanner/plugins/http/spider.py
yawast/scanner/plugins/http/version_checker.py
yawast/scanner/plugins/http/waf.py
yawast/scanner/plugins/http/applications/__init__.py
yawast/scanner/plugins/http/applications/jira.py
yawast/scanner/plugins/http/applications/wordpress.py
yawast/scanner/plugins/http/applications/generic/__init__.py
yawast-0.11.0.dist-info/LICENSE
yawast-0.11.0.dist-info/METADATA
yawast-0.11.0.dist-info/WHEEL
yawast-0.11.0.dist-info/entry_points.txt
yawast-0.11.0.dist-info/top_level.txt
yawast-0.11.0.dist-info/RECORD
