Metadata-Version: 2.1
Name: yawast
Version: 0.11.0
Summary: The YAWAST Antecedent Web Application Security Toolkit
Home-page: https://github.com/adamcaudill/yawast
Author: Adam Caudill
Author-email: adam@adamcaudill.com
License: MIT
Project-URL: Bug Reports, https://github.com/adamcaudill/yawast/issues
Project-URL: Source, https://github.com/adamcaudill/yawast
Project-URL: Changelog, https://github.com/adamcaudill/yawast/blob/master/CHANGELOG.md
Keywords: security tls ssl dns http scan vulnerability
Platform: UNKNOWN
Classifier: Development Status :: 4 - Beta
Classifier: License :: OSI Approved :: MIT License
Classifier: Environment :: Console
Classifier: Intended Audience :: Developers
Classifier: Intended Audience :: System Administrators
Classifier: Programming Language :: Python :: 3.6
Classifier: Programming Language :: Python :: 3.7
Classifier: Programming Language :: Python :: 3.8
Classifier: Natural Language :: English
Classifier: Topic :: Internet :: Name Service (DNS)
Classifier: Topic :: Internet :: WWW/HTTP
Classifier: Topic :: System :: Networking
Classifier: Topic :: Software Development :: Testing
Classifier: Topic :: Security
Requires-Python: >=3.7
Requires-Dist: appdirs
Requires-Dist: asn1crypto
Requires-Dist: attrs
Requires-Dist: beautifulsoup4
Requires-Dist: cached-property
Requires-Dist: cerberus
Requires-Dist: certifi
Requires-Dist: cffi
Requires-Dist: chardet
Requires-Dist: colorama
Requires-Dist: cryptography
Requires-Dist: distlib
Requires-Dist: dnspython
Requires-Dist: first
Requires-Dist: idna
Requires-Dist: importlib-metadata
Requires-Dist: jsonschema
Requires-Dist: more-itertools
Requires-Dist: nassl
Requires-Dist: ordered-set
Requires-Dist: orderedmultidict
Requires-Dist: packaging
Requires-Dist: pep517
Requires-Dist: pip-shims
Requires-Dist: plette
Requires-Dist: psutil
Requires-Dist: publicsuffixlist
Requires-Dist: pycparser
Requires-Dist: pyparsing
Requires-Dist: python-dateutil
Requires-Dist: requests
Requires-Dist: requests-mock
Requires-Dist: requirementslib
Requires-Dist: selenium
Requires-Dist: six
Requires-Dist: soupsieve
Requires-Dist: sslyze
Requires-Dist: tls-parser
Requires-Dist: toml
Requires-Dist: tomlkit
Requires-Dist: urllib3
Requires-Dist: validator-collection
Requires-Dist: vistir
Requires-Dist: wheel
Requires-Dist: yawast
Requires-Dist: zipp
